{
  "unpublishedPage": {
    "name": "Condutor",
    "slug": "condutor",
    "layouts": [
      {
        "viewMode": false,
        "dsl": {
          "widgetName": "MainContainer",
          "backgroundColor": "none",
          "rightColumn": 1224,
          "snapColumns": 64,
          "detachFromLayout": true,
          "widgetId": "0",
          "topRow": 0,
          "bottomRow": 570,
          "containerStyle": "none",
          "snapRows": 69,
          "parentRowSpace": 1,
          "type": "CANVAS_WIDGET",
          "canExtend": true,
          "version": 89,
          "minHeight": 710,
          "parentColumnSpace": 1,
          "dynamicBindingPathList": [],
          "leftColumn": 0
        },
        "layoutOnLoadActions": [
          [
            {
              "id": "Condutor_get",
              "name": "get",
              "confirmBeforeExecute": false,
              "pluginType": "API",
              "jsonPathKeys": [
                "appsmith.store.jwt"
              ],
              "timeoutInMillisecond": 10000
            },
            {
              "id": "Condutor_getUnidades",
              "name": "getUnidades",
              "confirmBeforeExecute": false,
              "pluginType": "API",
              "jsonPathKeys": [
                "appsmith.store.jwt"
              ],
              "timeoutInMillisecond": 10000
            }
          ]
        ],
        "layoutOnLoadActionErrors": [],
        "validOnPageLoadActions": true,
        "id": "Condutor",
        "deleted": false,
        "policies": [],
        "userPermissions": []
      }
    ],
    "userPermissions": [],
    "policies": [],
    "isHidden": false
  },
  "deleted": false,
  "gitSyncId": "65c281a7ed663e5cca363ff4_65d653bec20f0956f327f161"
}